PaPDF/PaPDF.py
PaPDF/TrueType.py
PaPDF/__init__.py
PaPDF-1.1.8.dist-info/LICENSE
PaPDF-1.1.8.dist-info/METADATA
PaPDF-1.1.8.dist-info/WHEEL
PaPDF-1.1.8.dist-info/top_level.txt
PaPDF-1.1.8.dist-info/RECORD
