Metadata-Version: 2.1
Name: PaPDF
Version: 1.1.8
Summary: A python package to create PDF files.
Home-page: https://github.com/gcoppex/PaPDF
Author: GCoppex
Author-email: g.coppex@gmail.com
Classifier: Programming Language :: Python :: 3
Classifier: License :: OSI Approved :: MIT License
Classifier: Operating System :: OS Independent
Requires-Python: >=3.5
License-File: LICENSE
